xmen/__init__.py
xmen/analysis.py
xmen/cli/__init__.py
xmen/cli/cli.py
xmen/cli/dict.py
xmen/cli/index.py
xmen/cli/utils.py
xmen/confhelper.py
xmen/data/__init__.py
xmen/data/abbrevations.py
xmen/data/deduplication.py
xmen/data/filter.py
xmen/data/indexed_dataset.py
xmen/data/integrations.py
xmen/data/merge_concepts.py
xmen/data/retired_cuis.py
xmen/data/sampling.py
xmen/data/semantic_groups.py
xmen/data/semantic_types.py
xmen/data/simplification.py
xmen/data/translation.py
xmen/data/util.py
xmen/evaluation.py
xmen/ext/neleval/annotation.py
xmen/ext/neleval/configs.py
xmen/ext/neleval/document.py
xmen/ext/neleval/evaluate.py
xmen/ext/neleval/prepare.py
xmen/ext/sapbert/LICENSE
xmen/ext/sapbert/README.md
xmen/ext/sapbert/requirements.txt
xmen/ext/sapbert/src/__init__.py
xmen/ext/sapbert/src/data_loader.py
xmen/ext/sapbert/src/metric_learning.py
xmen/ext/sapbert/train/.gitignore
xmen/ext/sapbert/train/pretrain.sh
xmen/ext/sapbert/train/train.py
xmen/ext/sapbert/train/xling_train.sh
xmen/ext/scispacy/umls_utils.py
xmen/kb.py
xmen/linkers/__init__.py
xmen/linkers/ensemble.py
xmen/linkers/faiss_indexer.py
xmen/linkers/model_wrapper.py
xmen/linkers/sap_bert_linker.py
xmen/linkers/tf_idf_ngram_linker.py
xmen/linkers/util.py
xmen/log.py
xmen/reranking/__init__.py
xmen/reranking/cross_encoder.py
xmen/reranking/list_wise.py
xmen/reranking/multiple_choice_util.py
xmen/reranking/ranking_util.py
xmen/reranking/rule_based.py
xmen/reranking/scored_cross_encoder.py
xmen/resources/.gitkeep
xmen/resources/Readme.md
xmen/resources/SemGroups-v03.txt
xmen/resources/SemGroups.txt
xmen/umls.py
xmen-1.0.8.dist-info/LICENSE
xmen-1.0.8.dist-info/METADATA
xmen-1.0.8.dist-info/WHEEL
xmen-1.0.8.dist-info/entry_points.txt
xmen-1.0.8.dist-info/RECORD
