Metadata-Version: 2.1
Name: xmen
Version: 1.0.8
Summary: An extensible toolkit for Cross-lingual (x) Medical Entity Normalization.
Home-page: https://github.com/hpi-dhc/xmen
License: Apache-2.0
Author: Florian Borchert
Author-email: florian.borchert@hpi.de
Requires-Python: >=3.8,<3.11
Classifier: License :: OSI Approved :: Apache Software License
Classifier: Programming Language :: Python :: 3
Classifier: Programming Language :: Python :: 3.8
Classifier: Programming Language :: Python :: 3.9
Classifier: Programming Language :: Python :: 3.10
Requires-Dist: datasets (>=2.0.0,<3.0.0)
Requires-Dist: faiss-cpu (>=1.7.1,<2.0.0) ; sys_platform != "linux" or platform_machine != "x86_64"
Requires-Dist: faiss-gpu (>=1.7.1,<2.0.0) ; sys_platform == "linux" and platform_machine == "x86_64"
Requires-Dist: langcodes (>=3.3.0,<4.0.0)
Requires-Dist: lxml (>=4.8.0,<5.0.0)
Requires-Dist: neleval (>=3.1.1,<4.0.0)
Requires-Dist: numpy (>=1.21,<2.0)
Requires-Dist: omegaconf (>=2.3.0,<3.0.0)
Requires-Dist: orjson (>=3.9.1,<4.0.0)
Requires-Dist: protobuf (>=3.20.0,<4.0.0)
Requires-Dist: pytorch-metric-learning (==0.9.98.dev1)
Requires-Dist: rich (>=12.3.0,<13.0.0)
Requires-Dist: scispacy (>=0.5.2,<0.6.0)
Requires-Dist: sentence-transformers (>=2.2.2,<3.0.0)
Requires-Dist: sentencepiece (>=0.1.96,<0.2.0)
Requires-Dist: torch (>=1.13.0,!=2.0.1,!=2.1.0)
Requires-Dist: transformers (>=4.17.0,<5.0.0)
Project-URL: Repository, https://github.com/hpi-dhc/xmen
